lib3.py
lib3-0.1.0.dist-info/LICENSE
lib3-0.1.0.dist-info/METADATA
lib3-0.1.0.dist-info/WHEEL
lib3-0.1.0.dist-info/entry_points.txt
lib3-0.1.0.dist-info/RECORD
